senMail/__init__.py
senMail/sendMail.py
senMail-0.0.1.dist-info/METADATA
senMail-0.0.1.dist-info/WHEEL
senMail-0.0.1.dist-info/top_level.txt
senMail-0.0.1.dist-info/RECORD
