Metadata-Version: 2.1
Name: senMail
Version: 0.0.1
Summary: Email sending package
Home-page: UNKNOWN
Author: Chandira Jananath(CjE)
Author-email: dhdevcj@gmail.com
License: UNKNOWN
Keywords: python,email,networking,sendmail,api,cje,pythoneasy
Platform: UNKNOWN
Classifier: Development Status :: 1 - Planning
Classifier: Intended Audience :: Developers
Classifier: Programming Language :: Python :: 3
Classifier: Operating System :: Unix
Classifier: Operating System :: Microsoft :: Windows
Requires-Dist: email
Requires-Dist: sendgrid
Requires-Dist: smtplib
Requires-Dist: ssl
Requires-Dist: yagmail
